piperss/__init__.py
piperss/__version__.py
piperss/main.py
piperss/pipeDisplay.py
piperss/pipeFormat.py
piperss/pipeList.py
piperss/pipeSelection.py
piperss/theme.py
piperss-0.1.8.dist-info/licenses/LICENSE
piperss-0.1.8.dist-info/METADATA
piperss-0.1.8.dist-info/WHEEL
piperss-0.1.8.dist-info/entry_points.txt
piperss-0.1.8.dist-info/top_level.txt
piperss-0.1.8.dist-info/RECORD
